{"chrome://browser/content/browser.xhtml":{"main-window":{"sizemode":"maximized","screenX":"104","screenY":"104","width":"959","height":"1045"},"sidebar-box":{"sidebarcommand":"","style":""},"sidebar-title":{"value":""}},"chrome://browser/content/places/places.xhtml":{"placesContentTags":{"ordinal":"3"},"placesContentUrl":{"ordinal":"5"},"placesContentDate":{"ordinal":"7"},"placesContentVisitCount":{"ordinal":"9"},"placesContentDateAdded":{"ordinal":"11"},"placesContentLastModified":{"ordinal":"13"},"places":{"screenX":"104","screenY":"144","width":"800","height":"500","sizemode":"normal"},"place:CqewroxEONFH0b8ILWSXYA==":{"open":"true"}}}